{
  "type": "Feature",
  "properties": {
    "iso:country":"EE",
    "sg:address":"Akadeemia tee 19",
    "sg:city":"Tallinn",
    "sg:classifiers":[
        {
            "category":"Manufacturing",
            "subcategory":"Electronics",
            "type":"Manufacturing & Wholesale Goods"
        }
    ],
    "sg:postcode":"12618",
    "sg:tags":[
        "video-calling",
        "television",
        "videophone",
        "tv",
        "consumer-electronics",
        "set-top-box"
    ],
    "sg:website":"http://www.inkspin1.com",
    "wof:name":"Inkspin1",
    "wof:placetype":"venue"
},
  "geometry": {"coordinates":[24.658767,59.397629],"type":"Point"}
}